odoo/addons/mrp_bom_component_menu/README.rst
odoo/addons/mrp_bom_component_menu/__init__.py
odoo/addons/mrp_bom_component_menu/__manifest__.py
odoo/addons/mrp_bom_component_menu/i18n/de.po
odoo/addons/mrp_bom_component_menu/i18n/es.po
odoo/addons/mrp_bom_component_menu/i18n/it.po
odoo/addons/mrp_bom_component_menu/i18n/mrp_bom_component_menu.pot
odoo/addons/mrp_bom_component_menu/i18n/pt_BR.po
odoo/addons/mrp_bom_component_menu/i18n/zh_CN.po
odoo/addons/mrp_bom_component_menu/readme/CONTRIBUTORS.md
odoo/addons/mrp_bom_component_menu/readme/DESCRIPTION.md
odoo/addons/mrp_bom_component_menu/readme/USAGE.md
odoo/addons/mrp_bom_component_menu/static/description/icon.png
odoo/addons/mrp_bom_component_menu/static/description/index.html
odoo/addons/mrp_bom_component_menu/views/mrp_bom_component_view.xml
odoo_addon_mrp_bom_component_menu-19.0.1.0.0.2.dist-info/METADATA
odoo_addon_mrp_bom_component_menu-19.0.1.0.0.2.dist-info/WHEEL
odoo_addon_mrp_bom_component_menu-19.0.1.0.0.2.dist-info/top_level.txt
odoo_addon_mrp_bom_component_menu-19.0.1.0.0.2.dist-info/RECORD
